pynsm/__init__.py
pynsm/_version.py
pynsm/arch/__init__.py
pynsm/arch/base.py
pynsm/arch/similarity.py
pynsm/util/__init__.py
pynsm/util/validation.py
pynsm-1.0.1.dist-info/LICENSE
pynsm-1.0.1.dist-info/METADATA
pynsm-1.0.1.dist-info/WHEEL
pynsm-1.0.1.dist-info/top_level.txt
pynsm-1.0.1.dist-info/RECORD
