Metadata-Version: 2.1
Name: pynsm
Version: 1.0.1
Summary: A PyTorch implementation of non-negative similarity matching
Author-email: Tiberiu Tesileanu <ttesileanu@gmail.com>, Shagesh Sridharan <shagesh1996@gmail.com>, Yanis Bahroun <ybahroun@flatironinstitute.org>
License: MIT License
Project-URL: Source, https://github.com/Shagesh/pytorch-NSM
Project-URL: Docs, https://pynsm.readthedocs.io
Keywords: neural network,biology,research
Classifier: License :: OSI Approved :: MIT License
Classifier: Programming Language :: Python :: 3
Classifier: Intended Audience :: Science/Research
Requires-Python: >=3.8
License-File: LICENSE
Requires-Dist: numpy
Requires-Dist: torch
Provides-Extra: dev
Requires-Dist: pytest ; extra == 'dev'
Requires-Dist: matplotlib ; extra == 'dev'
Requires-Dist: seaborn ; extra == 'dev'
Requires-Dist: ipykernel ; extra == 'dev'
Requires-Dist: tqdm ; extra == 'dev'
Requires-Dist: torchvision ; extra == 'dev'
Requires-Dist: scikit-learn ; extra == 'dev'
Provides-Extra: docs
Requires-Dist: mkdocs ; extra == 'docs'
Requires-Dist: mkdocstrings[python] ; extra == 'docs'
Requires-Dist: mkdocs-gen-files ; extra == 'docs'
Requires-Dist: mkdocs-literate-nav ; extra == 'docs'
Requires-Dist: mkdocs-jupyter ; extra == 'docs'
Requires-Dist: black ; extra == 'docs'
